{"lastUsed":1650032574094,"path":"C:\/eclipseworkspace2022-03-2","projectCount":4,"recentFiles":[{"path":"\/Servlet3\/src\/main\/java\/request\/methods","parentWorkspace":"C:\/eclipseworkspace2022-03-2","name":"RequestMethodsServlet.java","lastModified":1649856049399,"locationURI":"file:\/C:\/eclipseworkspace2022-03-2\/Servlet3\/src\/main\/java\/request\/methods\/RequestMethodsServlet.java"},{"path":"\/Servlet3\/src\/main\/java\/response\/cookie","parentWorkspace":"C:\/eclipseworkspace2022-03-2","name":"ResponseCookieServlet.java","lastModified":1649934259198,"locationURI":"file:\/C:\/eclipseworkspace2022-03-2\/Servlet3\/src\/main\/java\/response\/cookie\/ResponseCookieServlet.java"},{"path":"\/Servlet2\/src\/main\/java\/servletContext","parentWorkspace":"C:\/eclipseworkspace2022-03-2","name":"ContextServlet.java","lastModified":1649849683899,"locationURI":"file:\/C:\/eclipseworkspace2022-03-2\/Servlet2\/src\/main\/java\/servletContext\/ContextServlet.java"},{"path":"\/Servlet3\/src\/main\/java\/attributes","parentWorkspace":"C:\/eclipseworkspace2022-03-2","name":"SessionAttributeServlet.java","lastModified":1650023570404,"locationURI":"file:\/C:\/eclipseworkspace2022-03-2\/Servlet3\/src\/main\/java\/attributes\/SessionAttributeServlet.java"},{"path":"\/Servlet4\/src\/main\/webapp","parentWorkspace":"C:\/eclipseworkspace2022-03-2","name":"person.jsp","lastModified":1650026121429,"locationURI":"file:\/C:\/eclipseworkspace2022-03-2\/Servlet4\/src\/main\/webapp\/person.jsp"},{"path":"\/Servlet3\/src\/main\/webapp","parentWorkspace":"C:\/eclipseworkspace2022-03-2","name":"formPost.html","lastModified":1649850579533,"locationURI":"file:\/C:\/eclipseworkspace2022-03-2\/Servlet3\/src\/main\/webapp\/formPost.html"},{"path":"\/Servlet3\/src\/main\/java\/attributes","parentWorkspace":"C:\/eclipseworkspace2022-03-2","name":"RequestAttributeServlet.java","lastModified":1650024378056,"locationURI":"file:\/C:\/eclipseworkspace2022-03-2\/Servlet3\/src\/main\/java\/attributes\/RequestAttributeServlet.java"},{"path":"\/Servlet3\/src\/main\/java\/response\/encoding","parentWorkspace":"C:\/eclipseworkspace2022-03-2","name":"ResponseEncodingServlet.java","lastModified":1650024815260,"locationURI":"file:\/C:\/eclipseworkspace2022-03-2\/Servlet3\/src\/main\/java\/response\/encoding\/ResponseEncodingServlet.java"},{"path":"\/Servlet1\/src\/main\/java\/_01\/helloservlet","parentWorkspace":"C:\/Users\/eclipseworkspace2022-03-2","name":"AnnotationServlet.java","locationURI":"file:\/C:\/eclipseworkspace2022-03-2\/Servlet1\/src\/main\/java\/_01\/helloservlet\/AnnotationServlet.java"},{"path":"\/Servlet4\/src\/main\/java\/listener","parentWorkspace":"C:\/eclipseworkspace2022-03-2","name":"ServletContextListenerImpl.java","lastModified":1650029455649,"locationURI":"file:\/C:\/eclipseworkspace2022-03-2\/Servlet4\/src\/main\/java\/listener\/ServletContextListenerImpl.java"},{"path":"\/Servlet3\/src\/main\/java\/getRequestParams","parentWorkspace":"C:\/eclipseworkspace2022-03-2","name":"RequestGetForm.java","lastModified":1649854835012,"locationURI":"file:\/C:\/eclipseworkspace2022-03-2\/Servlet3\/src\/main\/java\/getRequestParams\/RequestGetForm.java"},{"path":"\/Servlet3\/src\/main\/java\/attributes","parentWorkspace":"C:\/eclipseworkspace2022-03-2","name":"ContextAttributeServlet.java","lastModified":1650023140331,"locationURI":"file:\/C:\/eclipseworkspace2022-03-2\/Servlet3\/src\/main\/java\/attributes\/ContextAttributeServlet.java"},{"path":"\/Servlet2\/src\/main\/java\/ServletConfig","parentWorkspace":"C:\/eclipseworkspace2022-03-2","name":"ConfigServlet.java","lastModified":1649836670181,"locationURI":"file:\/C:\/eclipseworkspace2022-03-2\/Servlet2\/src\/main\/java\/ServletConfig\/ConfigServlet.java"},{"path":"\/Servlet2\/src\/main\/webapp\/WEB-INF","parentWorkspace":"C:\/eclipseworkspace2022-03-2","name":"web.xml","lastModified":1649837143810,"locationURI":"file:\/C:\/eclipseworkspace2022-03-2\/Servlet2\/src\/main\/webapp\/WEB-INF\/web.xml"},{"path":"\/Servlet4\/src\/main\/java\/session","parentWorkspace":"C:\/eclipseworkspace2022-03-2","name":"SessionServlet.java","lastModified":1650032574275,"locationURI":"file:\/C:\/eclipseworkspace2022-03-2\/Servlet4\/src\/main\/java\/session\/SessionServlet.java"},{"path":"\/Servlet3\/src\/main\/java\/getRequestParams","parentWorkspace":"C:\/eclipseworkspace2022-03-2","name":"RequestPostForm.java","lastModified":1649851539062,"locationURI":"file:\/C:\/eclipseworkspace2022-03-2\/Servlet3\/src\/main\/java\/getRequestParams\/RequestPostForm.java"},{"path":"\/Servlet4\/src\/main\/java\/mvc","parentWorkspace":"C:\/eclipseworkspace2022-03-2","name":"PersonServlet.java","lastModified":1650029455650,"locationURI":"file:\/C:\/eclipseworkspace2022-03-2\/Servlet4\/src\/main\/java\/mvc\/PersonServlet.java"},{"path":"\/Servlet4\/src\/main\/webapp\/WEB-INF","parentWorkspace":"C:\/eclipseworkspace2022-03-2","name":"web.xml","lastModified":1650029646784,"locationURI":"file:\/C:\/eclipseworkspace2022-03-2\/Servlet4\/src\/main\/webapp\/WEB-INF\/web.xml"},{"path":"\/Servlet3\/src\/main\/java\/response\/header","parentWorkspace":"C:\/eclipseworkspace2022-03-2","name":"ResponseHeaderServlet.java","lastModified":1649922660107,"locationURI":"file:\/C:\/eclipseworkspace2022-03-2\/Servlet3\/src\/main\/java\/response\/header\/ResponseHeaderServlet.java"},{"path":"\/Servlet3\/src\/main\/java\/attributes","parentWorkspace":"C:\/eclipseworkspace2022-03-2","name":"SessionGetAttributeServlet.java","lastModified":1650023693380,"locationURI":"file:\/C:\/eclipseworkspace2022-03-2\/Servlet3\/src\/main\/java\/attributes\/SessionGetAttributeServlet.java"},{"path":"\/Servlet3\/src\/main\/java\/attributes","parentWorkspace":"C:\/eclipseworkspace2022-03-2","name":"ContextGetAttributeServlet.java","lastModified":1650023140331,"locationURI":"file:\/C:\/eclipseworkspace2022-03-2\/Servlet3\/src\/main\/java\/attributes\/ContextGetAttributeServlet.java"},{"path":"\/Servlet1\/src\/main\/webapp\/WEB-INF","parentWorkspace":"C:\/Users\/eclipseworkspace2022-03-2","name":"web.xml","locationURI":"file:\/C:\/eclipseworkspace2022-03-2\/Servlet1\/src\/main\/webapp\/WEB-INF\/web.xml"},{"path":"\/Servlet3\/src\/main\/webapp","parentWorkspace":"C:\/eclipseworkspace2022-03-2","name":"formGet.html","lastModified":1649853424448,"locationURI":"file:\/C:\/eclipseworkspace2022-03-2\/Servlet3\/src\/main\/webapp\/formGet.html"},{"path":"\/Servlet4\/src\/main\/java\/listener","parentWorkspace":"C:\/eclipseworkspace2022-03-2","name":"ServletRequestListenerImpl.java","lastModified":1650030768505,"locationURI":"file:\/C:\/eclipseworkspace2022-03-2\/Servlet4\/src\/main\/java\/listener\/ServletRequestListenerImpl.java"},{"path":"\/Servlet2\/src\/main\/java\/LifecycleServlet","parentWorkspace":"C:\/eclipseworkspace2022-03-2","name":"LifecycleServlet.java","lastModified":1649836670181,"locationURI":"file:\/C:\/eclipseworkspace2022-03-2\/Servlet2\/src\/main\/java\/LifecycleServlet\/LifecycleServlet.java"},{"path":"\/Servlet3\/src\/main\/java\/response\/cookie","parentWorkspace":"C:\/eclipseworkspace2022-03-2","name":"ResponseGetCookieServlet.java","lastModified":1649934656754,"locationURI":"file:\/C:\/eclipseworkspace2022-03-2\/Servlet3\/src\/main\/java\/response\/cookie\/ResponseGetCookieServlet.java"},{"path":"\/Servlet2\/src\/main\/java\/ServletConfig","parentWorkspace":"C:\/eclipseworkspace2022-03-2","name":"AnnotationConfigServlet.java","lastModified":1649836670181,"locationURI":"file:\/C:\/eclipseworkspace2022-03-2\/Servlet2\/src\/main\/java\/ServletConfig\/AnnotationConfigServlet.java"},{"path":"\/Servlet3\/src\/main\/java\/download","parentWorkspace":"C:\/eclipseworkspace2022-03-2","name":"DownloadServlet.java","lastModified":1649936697836,"locationURI":"file:\/C:\/eclipseworkspace2022-03-2\/Servlet3\/src\/main\/java\/download\/DownloadServlet.java"},{"path":"\/Servlet3\/src\/main\/java\/response\/send\/redirect","parentWorkspace":"C:\/eclipseworkspace2022-03-2","name":"ResponseSendRedirect.java","lastModified":1650007013016,"locationURI":"file:\/C:\/eclipseworkspace2022-03-2\/Servlet3\/src\/main\/java\/response\/send\/redirect\/ResponseSendRedirect.java"},{"path":"\/Servlet3\/src\/main\/java\/attributes","parentWorkspace":"C:\/eclipseworkspace2022-03-2","name":"RequestGetAttributeServlet.java","lastModified":1650024609257,"locationURI":"file:\/C:\/eclipseworkspace2022-03-2\/Servlet3\/src\/main\/java\/attributes\/RequestGetAttributeServlet.java"},{"path":"\/Servlet1\/src\/main\/java\/_01\/helloservlet","parentWorkspace":"C:\/Users\/eclipseworkspace2022-03-2","name":"MyFirstServlet.java","locationURI":"file:\/C:\/eclipseworkspace2022-03-2\/Servlet1\/src\/main\/java\/_01\/helloservlet\/MyFirstServlet.java"}]}